{
  "main": {
    "name":"",
    "occupation":"",
    "company":"",
    "companyLink":"",
    "description":"",
    "image":"profilepic.jpg",
    "bio":["Able to create strong visual content based on given criteria, this content could be posters, banners, logos, interfaces or video advertisements.", "Familiar with design software and technologies (Illustrator, Photoshop, After Effect...etc).", "Brainstorms new and creative ideas and understands the criteria of a project to deliver a carefully crafted design.", "Good experience with social media platforms especially Facebook as I have worked in online marketing before joining Novartis and I own many facebook pages which have large number of followers as mentioned below."],
    "email": "peter2008ps@gmail.com",
    "phone": "012-78-78-7115",
    "address":{
      "street":"",
      "city":"",
      "state":"Cairo",
      "zip": ""
    },
    "website": "https://app.netlify.com/teams/abanoubmesiha/sites",
    "resumedownload":"https://www.dropbox.com/s/ufgb8zylwbovres/abanoub%20ayoub%20cv.docx?dl=0",
    "social":[
      {
        "name":"facebook",
        "url":"https://www.facebook.com/Bony.mese7a",
        "className":"fa fa-facebook"
      },
      {
        "name":"linkedin",
        "url":"https://www.linkedin.com/in/abanoub-ayoub-025890b7/",
        "className":"fa fa-linkedin"
      },
      {
        "name":"github",
        "url":"https://github.com/abanoubmesiha/",
        "className":"fa fa-github"
      },
      {
        "name":"stackoverflow",
        "url":"https://stackoverflow.com/users/12149687/abanoub-meseha",
        "className":"fa fa-stack-overflow"
      }
    ]
  },
  "resume":{
    "education":[
      {
        "school":"KFS University of Veterinary Medicine",
        "degree":"Bachelor",
        "graduated":"June 2016",
        "description":"Bachelor's degree at veterinary surgery and medicine."
      }
    ],
    "courses":[
      {
        "name":"CS50",
        "date":"Jan 2020"
      },
      {
        "name":"React Testing with Jest and Enzyme",
        "date":"October 2020",
        "link":"https://www.udemy.com/course/react-testing-with-jest-and-enzyme/"
      }
    ],
    "work":[
      {
        "company":"Terkwaz Business Solutions",
        "companyLink":"https://terkwaz.com/",
        "title":"Front End Developer",
        "from":"04/2020",
        "to":"now",
        "description":"",
        "description2":["Joind the Front-end team of creating and maintaing blinklos.com", "Add features to Hemma, Riot, and Careers. (Terkwaz Projects)"]
      },
      {
        "company":"DHS Arabia",
        "companyLink":"https://www.dhsarabia.com/",
        "title":"Front End Developer",
        "from":"01/2019",
        "to":"04/2020",
        "description":"Working on MVC Core Views for DHS Arabia using bootstrap and javascript and put the foundations for a React project"
      }
    ],
    "skills":[
      {
        "name":"React",
        "level":"95%"
      },
      {
        "name":"Jest",
        "level":"50%"
      },
      {
        "name":"Angular",
        "level":"35%"
      },
      {
        "name":"MVC Core Views",
        "level":"40%"
      },
      {
        "name":"Javascript",
        "level":"85%"
      },
      {
        "name":"ES6",
        "level":"80%"
      },
      {
        "name":"Redux",
        "level":"75%"
      },
      {
        "name":"MonogoDB",
        "level":"50%"
      },
      {
        "name":"Express.js",
        "level":"50%"
      },
      {
        "name":"Node.js",
        "level":"50%"
      },
      {
        "name":"jQuery",
        "level":"60%"
      },
      {
        "name":"AJAX",
        "level":"50%"
      },
      {
        "name":"HTML5",
        "level":"65%"
      },
      {
        "name":"CSS3",
        "level":"50%"
      },
      {
        "name":"Bootstrap",
        "level":"50%"
      },
      {
        "name":"Sass",
        "level":"75%"
      },
      {
        "name":"Webpack",
        "level":"35%"
      },
      {
        "name":"Adobe Photoshop",
        "level":"80%"
      },
      {
        "name":"CorelDRAW",
        "level":"90%"
      },
      {
        "name":"Github",
        "level":"90%"
      }
      
    ]
  },
  "portfolio":{
    "projects": [
      {
        "title":"Moments of Pride 2021 video (Theme 1 )",
        "description":"",
        "category":"Novartis",
        "tags":"",
        "image":"Moments of Pride 2021 video (Theme 1 ).jpg",
        "url":"https://drive.google.com/file/d/12mZV4w3AbiiQPoD6OuvqidY7Wc2nQXLS/view",
        "modal":"#modal-1"
      },
      {
        "title":"Moments of Pride 2021 video (Theme 2 )",
        "description":"",
        "category":"Novartis",
        "tags":"",
        "image":"Moments of Pride 2021 video (Theme 2 ).jpg",
        "url":"https://drive.google.com/file/d/1S3CGzL41cSF9JhCJdTalM1i4eYAFA2ea/view",
        "modal":"#modal-2"
      },
      {
        "title":"MIDEA Video - Cycle Meeting 2021",
        "description":"",
        "category":"Novartis",
        "tags":"",
        "image":"MIDEA Video - Cycle Meeting 2021.jpg",
        "url":"https://drive.google.com/file/d/1XS2Rtqv8Rn9pRmu-078a05jUDDvVbhIK/view",
        "modal":"#modal-3"
      },
      {
        "title":"My idea in MIDEA 2020 Platform",
        "description":"",
        "category":"Novartis",
        "tags":"",
        "image":"My idea in MIDEA 2020 Platform.jpg",
        "url":"https://drive.google.com/file/d/1yNwijujGIF7OwBgPyQ7GsWGuEP14q6gy/view",
        "modal":"#modal-4"
      },
      {
        "title":"SFE video for APMA Awards 2020 competition (long version)",
        "description":"",
        "category":"Novartis",
        "tags":"",
        "image":"SFE video for APMA Awards 2020 (long version).jpg",
        "url":"https://drive.google.com/file/d/1Dyki6fji0QTrsdGLACh7KRmuvDrL8YOD/view",
        "modal":"#modal-5"
      },
      {
        "title":"SFE video for APMA Awards 2020 competition (short version)",
        "description":"",
        "category":"Novartis",
        "tags":"",
        "image":"SFE video for APMA Awards 2020 competition (short version).jpg",
        "url":"https://drive.google.com/file/d/1oJrmX2drx2X3ET2gv3WrfXnbIrAXKyRi/view",
        "modal":"#modal-6"
      },
      {
        "title":"My Manager Party Video",
        "description":"",
        "category":"Novartis",
        "tags":"",
        "image":"My Manager Party Video.jpg",
        "url":"https://drive.google.com/file/d/12yT59P_n4z5Umz-_X7doyGNbMGlo6zJz/view",
        "modal":"#modal-7"
      },
      {
        "title":"My video in NELP competition",
        "description":"",
        "category":"Novartis",
        "tags":"",
        "image":"My video in NELP competition.jpg",
        "url":"https://drive.google.com/file/d/1U1QnlSMDqdQCrq4TxfOM66_H7mQi9mzu/view",
        "modal":"#modal-8"
      },
      {
        "title":"Deticated to Medical staff martyrs due to Covid-19 epidemic",
        "description":"",
        "category":"Novartis",
        "tags":"",
        "image":"Deticated to Medical staff martyrs due to Covid-19 epidemic.jpg",
        "url":"https://drive.google.com/file/d/1Aa-bUOydwon94ArxWN28GcaXsbMrarpl/view",
        "modal":"#modal-9"
      },
      {
        "title": "",
        "description": "",
        "category": "Personal",
        "tags": "",
        "image": "001.jpg",
        "url": "/images/portfolio/001.jpg",
        "modal": "#modal-10"
      },
      {
        "title": "",
        "description": "",
        "category": "Personal",
        "tags": "",
        "image": "002.jpg",
        "url": "/images/portfolio/002.jpg",
        "modal": "#modal-11"
      },
      {
        "title": "",
        "description": "",
        "category": "Personal",
        "tags": "",
        "image": "003.jpg",
        "url": "/images/portfolio/003.jpg",
        "modal": "#modal-12"
      },
      {
        "title": "",
        "description": "",
        "category": "Personal",
        "tags": "",
        "image": "004.png",
        "url": "/images/portfolio/004.png",
        "modal": "#modal-13"
      },
      {
        "title": "",
        "description": "",
        "category": "Personal",
        "tags": "",
        "image": "005.png",
        "url": "/images/portfolio/005.png",
        "modal": "#modal-14"
      },
      {
        "title": "",
        "description": "",
        "category": "Personal",
        "tags": "",
        "image": "006.jpg",
        "url": "/images/portfolio/006.jpg",
        "modal": "#modal-15"
      },
      {
        "title": "",
        "description": "",
        "category": "Personal",
        "tags": "",
        "image": "007.jpg",
        "url": "/images/portfolio/007.jpg",
        "modal": "#modal-16"
      },
      {
        "title": "",
        "description": "",
        "category": "Personal",
        "tags": "",
        "image": "008.jpg",
        "url": "/images/portfolio/008.jpg",
        "modal": "#modal-17"
      },
      {
        "title": "",
        "description": "",
        "category": "Personal",
        "tags": "",
        "image": "009.jpg",
        "url": "/images/portfolio/009.jpg",
        "modal": "#modal-18"
      },
      {
        "title": "",
        "description": "",
        "category": "Personal",
        "tags": "",
        "image": "010.jpg",
        "url": "/images/portfolio/010.jpg",
        "modal": "#modal-19"
      },
      {
        "title": "",
        "description": "",
        "category": "Personal",
        "tags": "",
        "image": "011.jpg",
        "url": "/images/portfolio/011.jpg",
        "modal": "#modal-20"
      },
      {
        "title": "",
        "description": "",
        "category": "Personal",
        "tags": "",
        "image": "012.jpg",
        "url": "/images/portfolio/012.jpg",
        "modal": "#modal-21"
      },
      {
        "title": "",
        "description": "",
        "category": "Personal",
        "tags": "",
        "image": "013.jpg",
        "url": "/images/portfolio/013.jpg",
        "modal": "#modal-22"
      },
      {
        "title": "",
        "description": "",
        "category": "Personal",
        "tags": "",
        "image": "014.jpg",
        "url": "/images/portfolio/014.jpg",
        "modal": "#modal-23"
      },
      {
        "title": "",
        "description": "",
        "category": "Personal",
        "tags": "",
        "image": "015.jpg",
        "url": "/images/portfolio/015.jpg",
        "modal": "#modal-24"
      },
      {
        "title": "",
        "description": "",
        "category": "Personal",
        "tags": "",
        "image": "016.jpeg",
        "url": "/images/portfolio/016.jpeg",
        "modal": "#modal-25"
      },
      {
        "title": "",
        "description": "",
        "category": "Personal",
        "tags": "",
        "image": "017.jpg",
        "url": "/images/portfolio/017.jpg",
        "modal": "#modal-26"
      },
      {
        "title": "",
        "description": "",
        "category": "Personal",
        "tags": "",
        "image": "018.jpg",
        "url": "/images/portfolio/018.jpg",
        "modal": "#modal-27"
      },
      {
        "title": "",
        "description": "",
        "category": "Personal",
        "tags": "",
        "image": "019.jpg",
        "url": "/images/portfolio/019.jpg",
        "modal": "#modal-28"
      },
      {
        "title": "",
        "description": "",
        "category": "Personal",
        "tags": "",
        "image": "020.jpg",
        "url": "/images/portfolio/020.jpg",
        "modal": "#modal-29"
      },
      {
        "title": "",
        "description": "",
        "category": "Personal",
        "tags": "",
        "image": "021.jpg",
        "url": "/images/portfolio/021.jpg",
        "modal": "#modal-30"
      },
      {
        "title": "",
        "description": "",
        "category": "Personal",
        "tags": "",
        "image": "022.jpg",
        "url": "/images/portfolio/022.jpg",
        "modal": "#modal-31"
      },
      {
        "title": "",
        "description": "",
        "category": "Personal",
        "tags": "",
        "image": "023.jpg",
        "url": "/images/portfolio/023.jpg",
        "modal": "#modal-32"
      },
      {
        "title": "",
        "description": "",
        "category": "Personal",
        "tags": "",
        "image": "024.jpg",
        "url": "/images/portfolio/024.jpg",
        "modal": "#modal-33"
      },
      {
        "title": "",
        "description": "",
        "category": "Personal",
        "tags": "",
        "image": "025.jpg",
        "url": "/images/portfolio/025.jpg",
        "modal": "#modal-34"
      },
      {
        "title": "",
        "description": "",
        "category": "Personal",
        "tags": "",
        "image": "026.png",
        "url": "/images/portfolio/026.png",
        "modal": "#modal-35"
      },
      {
        "title": "",
        "description": "",
        "category": "Personal",
        "tags": "",
        "image": "027.jpg",
        "url": "/images/portfolio/027.jpg",
        "modal": "#modal-36"
      },
      {
        "title": "",
        "description": "",
        "category": "Personal",
        "tags": "",
        "image": "028.png",
        "url": "/images/portfolio/028.png",
        "modal": "#modal-37"
      },
      {
        "title": "",
        "description": "",
        "category": "Personal",
        "tags": "",
        "image": "5.png",
        "url": "/images/portfolio/5.png",
        "modal": "#modal-38"
      }
    ]
  },
  "testimonials":{
    "testimonials":[
      {
        "text":"",
        "user":""
      }
    ]
  }
}
